sk_nlp/__init__.py
sk_nlp/data/chinese_synonyms.txt
sk_nlp/data/dirty_word.txt
sk_nlp/data/stopword/baidu_stopwords.txt
sk_nlp/data/stopword/cn_stopwords.txt
sk_nlp/data/stopword/hit_stopwords.txt
sk_nlp/data/stopword/scu_stopwords.txt
sk_nlp/data/stopword/wiki_stop_word.txt
sk_nlp/log/ml.txt
sk_nlp/nlp_feature_embedding/__init__.py
sk_nlp/nlp_feature_embedding/bert.py
sk_nlp/nlp_feature_embedding/similarity.py
sk_nlp/nlp_feature_embedding/w2v.py
sk_nlp/nlp_feature_extract/__init__.py
sk_nlp/nlp_feature_extract/feature.py
sk_nlp/nlp_feature_extract/text_filter.py
sk_nlp/nlp_feature_extract/tokenizer.py
sk_nlp/nlp_model/__init__.py
sk_nlp/util/__init__.py
sk_nlp/util/file.py
sk_nlp/util/file_conf.py
sk_nlp/util/io.py
sk_nlp/util/log.py
sk_nlp/util/tool.py
sk_nlp-0.1.9.dist-info/LICENSE
sk_nlp-0.1.9.dist-info/METADATA
sk_nlp-0.1.9.dist-info/WHEEL
sk_nlp-0.1.9.dist-info/top_level.txt
sk_nlp-0.1.9.dist-info/RECORD
