Metadata-Version: 2.1
Name: sk-nlp
Version: 0.1.9
Summary: nlp kit.
Home-page: https://github.com/me/myproject
Author: wengsongxiu
Author-email: wengsongxiu@mastercom.cn
License: MIT
Platform: UNKNOWN
Classifier: License :: OSI Approved :: MIT License
Classifier: Programming Language :: Python
Classifier: Programming Language :: Python :: 3
Classifier: Programming Language :: Python :: 3.6
Classifier: Programming Language :: Python :: Implementation :: CPython
Classifier: Programming Language :: Python :: Implementation :: PyPy
Requires-Python: >=3.6.0
Requires-Dist: numpy
Requires-Dist: scipy
Requires-Dist: tensorflow-gpu
Requires-Dist: bert4keras
Requires-Dist: sk-common
